hiperccat/.DS_Store
hiperccat/__init__.py
hiperccat/py.typed
hiperccat-0.0.1.dist-info/METADATA
hiperccat-0.0.1.dist-info/WHEEL
hiperccat-0.0.1.dist-info/entry_points.txt
hiperccat-0.0.1.dist-info/licenses/LICENSE
hiperccat-0.0.1.dist-info/RECORD
