Metadata-Version: 2.1
Name: hiperccat
Version: 0.0.1
Summary: tools for automating job creation and management for DFT calculations
Author-email: Ugochukwu Nwosu <ugognw@gmail.com>
License: MIT License
License-File: LICENSE
Keywords: automation,dft,hpc,matter modeling
Classifier: Development Status :: 1 - Planning
Classifier: Framework :: Sphinx
Classifier: Framework :: tox
Classifier: Intended Audience :: Science/Research
Classifier: License :: OSI Approved :: MIT License
Classifier: Natural Language :: English
Classifier: Operating System :: Microsoft :: Windows
Classifier: Operating System :: POSIX
Classifier: Operating System :: Unix
Classifier: Programming Language :: Python
Classifier: Programming Language :: Python :: 3
Classifier: Programming Language :: Python :: 3 :: Only
Classifier: Programming Language :: Python :: 3.7
Classifier: Programming Language :: Python :: 3.8
Classifier: Programming Language :: Python :: 3.9
Classifier: Programming Language :: Python :: 3.10
Classifier: Programming Language :: Python :: 3.11
Classifier: Programming Language :: Python :: 3.12
Classifier: Programming Language :: Python :: 3.13
Classifier: Programming Language :: Python :: Implementation :: CPython
Classifier: Programming Language :: Python :: Implementation :: PyPy
Classifier: Topic :: Scientific/Engineering :: Chemistry
Classifier: Topic :: Scientific/Engineering :: Physics
Requires-Python: >=3.7
Requires-Dist: ase>=3.22.1
Requires-Dist: emmet-core>=0.68.0
Requires-Dist: jinja2>=3.1.2
Requires-Dist: monty>=2022.4.26
Requires-Dist: numpy>=1.23.1
Requires-Dist: pydantic-settings
Requires-Dist: pydantic>=2
Requires-Dist: pymatgen>=2022.9.8
Requires-Dist: shortuuid>=1.0.9
Requires-Dist: typer[all]
Requires-Dist: typing-extensions
